tomorrowcities/__init__.py
tomorrowcities/core.py
tomorrowcities-0.0.2.dist-info/METADATA
tomorrowcities-0.0.2.dist-info/WHEEL
tomorrowcities-0.0.2.dist-info/licenses/LICENSE
tomorrowcities-0.0.2.dist-info/RECORD
