Metadata-Version: 2.1
Name: tomorrowcities
Version: 0.0.2
Summary: Tomorrow Cities' Python Library
Project-URL: Homepage, https://github.com/TomorrowsCities
Project-URL: Bug Tracker, https://github.com/TomorrowsCities
Author-email: Huseyin Kaya <hkayabilisim@gmail.com>, Prashant Rawal <prashantrawal@nset.org.np>, Erdem Ozer <ozerer@gmail.com>
License-File: LICENSE
Classifier: License :: OSI Approved :: MIT License
Classifier: Operating System :: OS Independent
Classifier: Programming Language :: Python :: 3
Requires-Python: >=3.7
